focus_app/__init__.py
focus_app/db.zip
focus_app/focus.py
metagenomics_focus-1.5.dist-info/COPYING
metagenomics_focus-1.5.dist-info/METADATA
metagenomics_focus-1.5.dist-info/WHEEL
metagenomics_focus-1.5.dist-info/entry_points.txt
metagenomics_focus-1.5.dist-info/top_level.txt
metagenomics_focus-1.5.dist-info/RECORD
