Metadata-Version: 2.1
Name: metagenomics-focus
Version: 1.5
Summary: FOCUS: An Agile Profiler for Metagenomic Data
Home-page: https://github.com/metageni/focus
Author: Genivaldo G.Z. Silva
Author-email: genivaldo.gueiros@gmail.com
License: UNKNOWN
Keywords: focus_app
Platform: UNKNOWN
Classifier: Development Status :: 2 - Pre-Alpha
Classifier: Intended Audience :: Developers
Classifier: Natural Language :: English
Classifier: Programming Language :: Python :: 3.6
Classifier: Topic :: Scientific/Engineering :: Bio-Informatics
Requires-Dist: numpy (>=1.12.1)
Requires-Dist: scipy (>=0.19.0)
